four-lane-traffic-light/traffic_light_4_lane.v
module traffic_light_4_lane(
    input clk,
    input rst,
    input pedestrian_ns,
    input pedestrian_ew,
    output reg ns_green,
    output reg ns_yellow,
    output reg ns_red,
    output reg ew_green,
    output reg ew_red,
    output reg ew_yellow
);

parameter s0 = 2'b00,  // ns_green
          s1 = 2'b01,  // ns_yellow
          s2 = 2'b10,  // ew_green
          s3 = 2'b11;  // ew_yellow

reg [1:0]state , next_state;
reg tick_time;
reg [3:0]timer;
//reg [25:0]count; //fsm clk is 50MHz so 26 bits is sufficient
reg [5:0]count;  // for testbench
// fsm clock logic
always @(posedge clk or posedge rst)begin
  
  if(rst)begin
    tick_time <= 0;
    count <= 0;
  end

   else if(count == 50 - 1) begin // to write testbench.
  //else if(count == 50000000 -1)begin
    tick_time <= 1;
    count <= 0;
  end

  else begin
    tick_time <= 0;
    count <= count + 1;
  end
end

// timer concept 
always @(posedge clk or posedge rst)begin
  
  if(rst)
  timer <= 0;

  else if(tick_time)begin
    if(state != next_state)
    timer <= 0;

    else 
    timer <= timer +1;
  end


end
always @(posedge clk or posedge rst)begin
  
  if(rst)
  state <= s0;

  else
  state <= next_state;
end

always @(*)begin
  next_state = state;

  case(state)

  // ns green
  s0 : begin
    if(timer == 15)
    next_state = s1;

    else if(timer >= 7 && pedestrian_ns)
    next_state = s1;

    else
    next_state = s0;
  end
  
  // ns_yellow
  s1 : begin
    if(timer == 4)
    next_state = s2;

    else 
    next_state = s1;
  end
  
  // ew_green
  s2 : begin
    if(timer == 15)
    next_state = s3;

    else if(timer >= 7 && pedestrian_ew)
    next_state = s3;

    else 
    next_state = s2;
  end
  
  // ew_yellow
  s3 : begin
    if(timer == 4)
    next_state = s0;
    
    else 
    next_state = s3;
  end

  default : next_state = s0;
 endcase
end

always @(*)begin
    ns_green  = 0;
    ns_yellow = 0;
    ns_red    = 0;
    ew_green  = 0;
    ew_red    = 0;
    ew_yellow = 0;
  case(state)

  s0 : begin
    ns_green =1;
    ew_red =1;
  end

  s1 : begin
    ns_yellow =1;
    ew_red =1;
  end

  s2 : begin
    ns_red = 1;
    ew_green =1;
  end

  s3 : begin
    ns_red = 1;
    ew_yellow =1;
  end
  endcase
end
endmodule

four-lane-traffic-light/tb_traffic_light_4_lane.v
`timescale 1ns/1ps

module tb_traffic_light_4_lane;
reg clk, rst, pedestrian_ew, pedestrian_ns;
wire ew_green, ew_red, ew_yellow, ns_green, ns_red, ns_yellow;

traffic_light_4_lane uut(
    .clk(clk),
    .rst(rst),
    .pedestrian_ew(pedestrian_ew),
    .pedestrian_ns(pedestrian_ns),
    .ew_green(ew_green),
    .ew_yellow(ew_yellow),
    .ew_red(ew_red),
    .ns_green(ns_green),
    .ns_yellow(ns_yellow),
    .ns_red(ns_red)
);

always #5 clk = ~clk;

initial begin
  
  $dumpfile("tb_traffic_light_4_lane.vcd");
  $dumpvars(0, tb_traffic_light_4_lane);
  // taken from gpt
  $monitor("Time=%0t | State=%0d | NS[G Y R]=%b %b %b | EW[G Y R]=%b %b %b | ped_ns=%b ped_ew=%b",
              $time, uut.state, ns_green, ns_yellow, ns_red,
              ew_green, ew_yellow, ew_red, pedestrian_ns, pedestrian_ew);

  clk =0;
  rst =1;
  pedestrian_ew =0;
  pedestrian_ns =0;

    #20;
    rst = 0;

    #2000;

    pedestrian_ew = 1;
    #20;
    pedestrian_ew = 0;

    #2000;

    pedestrian_ns = 1;
    #20;
    pedestrian_ns = 0;

    #100000;

    $finish;

end
endmodule

four-lane-traffic-light/tb_traffic_light_4_lane.vcd
$date
	Thu Feb 26 11:35:47 2026
$end
$version
	Icarus Verilog
$end
$timescale
	1ps
$end
$scope module tb_traffic_light_4_lane $end
$var wire 1 ! ns_yellow $end
$var wire 1 " ns_red $end
$var wire 1 # ns_green $end
$var wire 1 $ ew_yellow $end
$var wire 1 % ew_red $end
$var wire 1 & ew_green $end
$var reg 1 ' clk $end
$var reg 1 ( pedestrian_ew $end
$var reg 1 ) pedestrian_ns $end
$var reg 1 * rst $end
$scope module uut $end
$var wire 1 ' clk $end
$var wire 1 ( pedestrian_ew $end
$var wire 1 ) pedestrian_ns $end
$var wire 1 * rst $end
$var parameter 2 + s0 $end
$var parameter 2 , s1 $end
$var parameter 2 - s2 $end
$var parameter 2 . s3 $end
$var reg 6 / count [5:0] $end
$var reg 1 & ew_green $end
$var reg 1 % ew_red $end
$var reg 1 $ ew_yellow $end
$var reg 2 0 next_state [1:0] $end
$var reg 1 # ns_green $end
$var reg 1 " ns_red $end
$var reg 1 ! ns_yellow $end
$var reg 2 1 state [1:0] $end
$var reg 1 2 tick_time $end
$var reg 4 3 timer [3:0] $end
$upscope $end
$upscope $end
$enddefinitions $end
$comment Show the parameter values. $end
$dumpall
b11 .
b10 -
b1 ,
b0 +
$end
#0
$dumpvars
b0 3
02
b0 1
b0 0
b0 /
1*
0)
0(
0'
0&
1%
0$
1#
0"
0!
$end
#5000
1'
#10000
0'
#15000
1'
#20000
0'
0*
#25000
b1 /
1'
#30000
0'
#35000
b10 /
1'
#40000
0'
#45000
b11 /
1'
#50000
0'
#55000
b100 /
1'
#60000
0'
#65000
b101 /
1'
#70000
0'
#75000
b110 /
1'
#80000
0'
#85000
b111 /
1'
#90000
0'
#95000
b1000 /
1'
#100000
0'
#105000
b1001 /
1'
#110000
0'
#115000
b1010 /
1'
#120000
0'
#125000
b1011 /
1'
#130000
0'
#135000
b1100 /
1'
#140000
0'
#145000
b1101 /
1'
#150000
0'
#155000
b1110 /
1'
#160000
0'
#165000
b1111 /
1'
#170000
0'
#175000
b10000 /
1'
#180000
0'
#185000
b10001 /
1'
#190000
0'
#195000
b10010 /
1'
#200000
0'
#205000
b10011 /
1'
#210000
0'
#215000
b10100 /
1'
#220000
0'
#225000
b10101 /
1'
#230000
0'
#235000
b10110 /
1'
#240000
0'
#245000
b10111 /
1'
#250000
0'
#255000
b11000 /
1'
#260000
0'
#265000
b11001 /
1'
#270000
0'
#275000
b11010 /
1'
#280000
0'
#285000
b11011 /
1'
#290000
0'
#295000
b11100 /
1'
#300000
0'
#305000
b11101 /
1'
#310000
0'
#315000
b11110 /
1'
#320000
0'
#325000
b11111 /
1'
#330000
0'
#335000
b100000 /
1'
#340000
0'
#345000
b100001 /
1'
#350000
0'
#355000
b100010 /
1'
#360000
0'
#365000
b100011 /
1'
#370000
0'
#375000
b100100 /
1'
#380000
0'
#385000
b100101 /
1'
#390000
0'
#395000
b100110 /
1'
#400000
0'
#405000
b100111 /
1'
#410000
0'
#415000
b101000 /
1'
#420000
0'
#425000
b101001 /
1'
#430000
0'
#435000
b101010 /
1'
#440000
0'
#445000
b101011 /
1'
#450000
0'
#455000
b101100 /
1'
#460000
0'
#465000
b101101 /
1'
#470000
0'
#475000
b101110 /
1'
#480000
0'
#485000
b101111 /
1'
#490000
0'
#495000
b110000 /
1'
#500000
0'
#505000
b110001 /
1'
#510000
0'
#515000
b0 /
12
1'
#520000
0'
#525000
b1 3
b1 /
02
1'
#530000
0'
#535000
b10 /
1'
#540000
0'
#545000
b11 /
1'
#550000
0'
#555000
b100 /
1'
#560000
0'
#565000
b101 /
1'
#570000
0'
#575000
b110 /
1'
#580000
0'
#585000
b111 /
1'
#590000
0'
#595000
b1000 /
1'
#600000
0'
#605000
b1001 /
1'
#610000
0'
#615000
b1010 /
1'
#620000
0'
#625000
b1011 /
1'
#630000
0'
#635000
b1100 /
1'
#640000
0'
#645000
b1101 /
1'
#650000
0'
#655000
b1110 /
1'
#660000
0'
#665000
b1111 /
1'
#670000
0'
#675000
b10000 /
1'
#680000
0'
#685000
b10001 /
1'
#690000
0'
#695000
b10010 /
1'
#700000
0'
#705000
b10011 /
1'
#710000
0'
#715000
b10100 /
1'
#720000
0'
#725000
b10101 /
1'
#730000
0'
#735000
b10110 /
1'
#740000
0'
#745000
b10111 /
1'
#750000
0'
#755000
b11000 /
1'
#760000
0'
#765000
b11001 /
1'
#770000
0'
#775000
b11010 /
1'
#780000
0'
#785000
b11011 /
1'
#790000
0'
#795000
b11100 /
1'
#800000
0'
#805000
b11101 /
1'
#810000
0'
#815000
b11110 /
1'
#820000
0'
#825000
b11111 /
1'
#830000
0'
#835000
b100000 /
1'
#840000
0'
#845000
b100001 /
1'
#850000
0'
#855000
b100010 /
1'
#860000
0'
#865000
b100011 /
1'
#870000
0'
#875000
b100100 /
1'
#880000
0'
#885000
b100101 /
1'
#890000
0'
#895000
b100110 /
1'
#900000
0'
#905000
b100111 /
1'
#910000
0'
#915000
b101000 /
1'
#920000
0'
#925000
b101001 /
1'
#930000
0'
#935000
b101010 /
1'
#940000
0'
#945000
b101011 /
1'
#950000
0'
#955000
b101100 /
1'
#960000
0'
#965000
b101101 /
1'
#970000
0'
#975000
b101110 /
1'
#980000
0'
#985000
b101111 /
1'
#990000
0'
#995000
b110000 /
1'
#1000000
0'
#1005000
b110001 /
1'
#1010000
0'
#1015000
b0 /
12
1'
#1020000
0'
#1025000
b10 3
b1 /
02
1'
#1030000
0'
#1035000
b10 /
1'
#1040000
0'
#1045000
b11 /
1'
#1050000
0'
#1055000
b100 /
1'
#1060000
0'
#1065000
b101 /
1'
#1070000
0'
#1075000
b110 /
1'
#1080000
0'
#1085000
b111 /
1'
#1090000
0'
#1095000
b1000 /
1'
#1100000
0'
#1105000
b1001 /
1'
#1110000
0'
#1115000
b1010 /
1'
#1120000
0'
#1125000
b1011 /
1'
#1130000
0'
#1135000
b1100 /
1'
#1140000
0'
#1145000
b1101 /
1'
#1150000
0'
#1155000
b1110 /
1'
#1160000
0'
#1165000
b1111 /
1'
#1170000
0'
#1175000
b10000 /
1'
#1180000
0'
#1185000
b10001 /
1'
#1190000
0'
#1195000
b10010 /
1'
#1200000
0'
#1205000
b10011 /
1'
#1210000
0'
#1215000
b10100 /
1'
#1220000
0'
#1225000
b10101 /
1'
#1230000
0'
#1235000
b10110 /
1'
#1240000
0'
#1245000
b10111 /
1'
#1250000
0'
#1255000
b11000 /
1'
#1260000
0'
#1265000
b11001 /
1'
#1270000
0'
#1275000
b11010 /
1'
#1280000
0'
#1285000
b11011 /
1'
#1290000
0'
#1295000
b11100 /
1'
#1300000
0'
#1305000
b11101 /
1'
#1310000
0'
#1315000
b11110 /
1'
#1320000
0'
#1325000
b11111 /
1'
#1330000
0'
#1335000
b100000 /
1'
#1340000
0'
#1345000
b100001 /
1'
#1350000
0'
#1355000
b100010 /
1'
#1360000
0'
#1365000
b100011 /
1'
#1370000
0'
#1375000
b100100 /
1'
#1380000
0'
#1385000
b100101 /
1'
#1390000
0'
#1395000
b100110 /
1'
#1400000
0'
#1405000
b100111 /
1'
#1410000
0'
#1415000
b101000 /
1'
#1420000
0'
#1425000
b101001 /
1'
#1430000
0'
#1435000
b101010 /
1'
#1440000
0'
#1445000
b101011 /
1'
#1450000
0'
#1455000
b101100 /
1'
#1460000
0'
#1465000
b101101 /
1'
#1470000
0'
#1475000
b101110 /
1'
#1480000
0'
#1485000
b101111 /
1'
#1490000
0'
#1495000
b110000 /
1'
#1500000
0'
#1505000
b110001 /
1'
#1510000
0'
#1515000
b0 /
12
1'
#1520000
0'
#1525000
b11 3
b1 /
02
1'
#1530000
0'
#1535000
b10 /
1'
#1540000
0'
#1545000
b11 /
1'
#1550000
0'
#1555000
b100 /
1'
#1560000
0'
#1565000
b101 /
1'
#1570000
0'
#1575000
b110 /
1'
#1580000
0'
#1585000
b111 /
1'
#1590000
0'
#1595000
b1000 /
1'
#1600000
0'
#1605000
b1001 /
1'
#1610000
0'
#1615000
b1010 /
1'
#1620000
0'
#1625000
b1011 /
1'
#1630000
0'
#1635000
b1100 /
1'
#1640000
0'
#1645000
b1101 /
1'
#1650000
0'
#1655000
b1110 /
1'
#1660000
0'
#1665000
b1111 /
1'
#1670000
0'
#1675000
b10000 /
1'
#1680000
0'
#1685000
b10001 /
1'
#1690000
0'
#1695000
b10010 /
1'
#1700000
0'
#1705000
b10011 /
1'
#1710000
0'
#1715000
b10100 /
1'
#1720000
0'
#1725000
b10101 /
1'
#1730000
0'
#1735000
b10110 /
1'
#1740000
0'
#1745000
b10111 /
1'
#1750000
0'
#1755000
b11000 /
1'
#1760000
0'
#1765000
b11001 /
1'
#1770000
0'
#1775000
b11010 /
1'
#1780000
0'
#1785000
b11011 /
1'
#1790000
0'
#1795000
b11100 /
1'
#1800000
0'
#1805000
b11101 /
1'
#1810000
0'
#1815000
b11110 /
1'
#1820000
0'
#1825000
b11111 /
1'
#1830000
0'
#1835000
b100000 /
1'
#1840000
0'
#1845000
b100001 /
1'
#1850000
0'
#1855000
b100010 /
1'
#1860000
0'
#1865000
b100011 /
1'
#1870000
0'
#1875000
b100100 /
1'
#1880000
0'
#1885000
b100101 /
1'
#1890000
0'
#1895000
b100110 /
1'
#1900000
0'
#1905000
b100111 /
1'
#1910000
0'
#1915000
b101000 /
1'
#1920000
0'
#1925000
b101001 /
1'
#1930000
0'
#1935000
b101010 /
1'
#1940000
0'
#1945000
b101011 /
1'
#1950000
0'
#1955000
b101100 /
1'
#1960000
0'
#1965000
b101101 /
1'
#1970000
0'
#1975000
b101110 /
1'
#1980000
0'
#1985000
b101111 /
1'
#1990000
0'
#1995000
b110000 /
1'
#2000000
0'
#2005000
b110001 /
1'
#2010000
0'
#2015000
b0 /
12
1'
#2020000
0'
1(
#2025000
b100 3
b1 /
02
1'
#2030000
0'
#2035000
b10 /
1'
#2040000
0'
0(
#2045000
b11 /
1'
#2050000
0'
#2055000
b100 /
1'
#2060000
0'
#2065000
b101 /
1'
#2070000
0'
#2075000
b110 /
1'
#2080000
0'
#2085000
b111 /
1'
#2090000
0'
#2095000
b1000 /
1'
#2100000
0'
#2105000
b1001 /
1'
#2110000
0'
#2115000
b1010 /
1'
#2120000
0'
#2125000
b1011 /
1'
#2130000
0'
#2135000
b1100 /
1'
#2140000
0'
#2145000
b1101 /
1'
#2150000
0'
#2155000
b1110 /
1'
#2160000
0'
#2165000
b1111 /
1'
#2170000
0'
#2175000
b10000 /
1'
#2180000
0'
#2185000
b10001 /
1'
#2190000
0'
#2195000
b10010 /
1'
#2200000
0'
#2205000
b10011 /
1'
#2210000
0'
#2215000
b10100 /
1'
#2220000
0'
#2225000
b10101 /
1'
#2230000
0'
#2235000
b10110 /
1'
#2240000
0'
#2245000
b10111 /
1'
#2250000
0'
#2255000
b11000 /
1'
#2260000
0'
#2265000
b11001 /
1'
#2270000
0'
#2275000
b11010 /
1'
#2280000
0'
#2285000
b11011 /
1'
#2290000
0'
#2295000
b11100 /
1'
#2300000
0'
#2305000
b11101 /
1'
#2310000
0'
#2315000
b11110 /
1'
#2320000
0'
#2325000
b11111 /
1'
#2330000
0'
#2335000
b100000 /
1'
#2340000
0'
#2345000
b100001 /
1'
#2350000
0'
#2355000
b100010 /
1'
#2360000
0'
#2365000
b100011 /
1'
#2370000
0'
#2375000
b100100 /
1'
#2380000
0'
#2385000
b100101 /
1'
#2390000
0'
#2395000
b100110 /
1'
#2400000
0'
#2405000
b100111 /
1'
#2410000
0'
#2415000
b101000 /
1'
#2420000
0'
#2425000
b101001 /
1'
#2430000
0'
#2435000
b101010 /
1'
#2440000
0'
#2445000
b101011 /
1'
#2450000
0'
#2455000
b101100 /
1'
#2460000
0'
#2465000
b101101 /
1'
#2470000
0'
#2475000
b101110 /
1'
#2480000
0'
#2485000
b101111 /
1'
#2490000
0'
#2495000
b110000 /
1'
#2500000
0'
#2505000
b110001 /
1'
#2510000
0'
#2515000
b0 /
12
1'
#2520000
0'
#2525000
b101 3
b1 /
02
1'
#2530000
0'
#2535000
b10 /
1'
#2540000
0'
#2545000
b11 /
1'
#2550000
0'
#2555000
b100 /
1'
#2560000
0'
#2565000
b101 /
1'
#2570000
0'
#2575000
b110 /
1'
#2580000
0'
#2585000
b111 /
1'
#2590000
0'
#2595000
b1000 /
1'
#2600000
0'
#2605000
b1001 /
1'
#2610000
0'
#2615000
b1010 /
1'
#2620000
0'
#2625000
b1011 /
1'
#2630000
0'
#2635000
b1100 /
1'
#2640000
0'
#2645000
b1101 /
1'
#2650000
0'
#2655000
b1110 /
1'
#2660000
0'
#2665000
b1111 /
1'
#2670000
0'
#2675000
b10000 /
1'
#2680000
0'
#2685000
b10001 /
1'
#2690000
0'
#2695000
b10010 /
1'
#2700000
0'
#2705000
b10011 /
1'
#2710000
0'
#2715000
b10100 /
1'
#2720000
0'
#2725000
b10101 /
1'
#2730000
0'
#2735000
b10110 /
1'
#2740000
0'
#2745000
b10111 /
1'
#2750000
0'
#2755000
b11000 /
1'
#2760000
0'
#2765000
b11001 /
1'
#2770000
0'
#2775000
b11010 /
1'
#2780000
0'
#2785000
b11011 /
1'
#2790000
0'
#2795000
b11100 /
1'
#2800000
0'
#2805000
b11101 /
1'
#2810000
0'
#2815000
b11110 /
1'
#2820000
0'
#2825000
b11111 /
1'
#2830000
0'
#2835000
b100000 /
1'
#2840000
0'
#2845000
b100001 /
1'
#2850000
0'
#2855000
b100010 /
1'
#2860000
0'
#2865000
b100011 /
1'
#2870000
0'
#2875000
b100100 /
1'
#2880000
0'
#2885000
b100101 /
1'
#2890000
0'
#2895000
b100110 /
1'
#2900000
0'
#2905000
b100111 /
1'
#2910000
0'
#2915000
b101000 /
1'
#2920000
0'
#2925000
b101001 /
1'
#2930000
0'
#2935000
b101010 /
1'
#2940000
0'
#2945000
b101011 /
1'
#2950000
0'
#2955000
b101100 /
1'
#2960000
0'
#2965000
b101101 /
1'
#2970000
0'
#2975000
b101110 /
1'
#2980000
0'
#2985000
b101111 /
1'
#2990000
0'
#2995000
b110000 /
1'
#3000000
0'
#3005000
b110001 /
1'
#3010000
0'
#3015000
b0 /
12
1'
#3020000
0'
#3025000
b110 3
b1 /
02
1'
#3030000
0'
#3035000
b10 /
1'
#3040000
0'
#3045000
b11 /
1'
#3050000
0'
#3055000
b100 /
1'
#3060000
0'
#3065000
b101 /
1'
#3070000
0'
#3075000
b110 /
1'
#3080000
0'
#3085000
b111 /
1'
#3090000
0'
#3095000
b1000 /
1'
#3100000
0'
#3105000
b1001 /
1'
#3110000
0'
#3115000
b1010 /
1'
#3120000
0'
#3125000
b1011 /
1'
#3130000
0'
#3135000
b1100 /
1'
#3140000
0'
#3145000
b1101 /
1'
#3150000
0'
#3155000
b1110 /
1'
#3160000
0'
#3165000
b1111 /
1'
#3170000
0'
#3175000
b10000 /
1'
#3180000
0'
#3185000
b10001 /
1'
#3190000
0'
#3195000
b10010 /
1'
#3200000
0'
#3205000
b10011 /
1'
#3210000
0'
#3215000
b10100 /
1'
#3220000
0'
#3225000
b10101 /
1'
#3230000
0'
#3235000
b10110 /
1'
#3240000
0'
#3245000
b10111 /
1'
#3250000
0'
#3255000
b11000 /
1'
#3260000
0'
#3265000
b11001 /
1'
#3270000
0'
#3275000
b11010 /
1'
#3280000
0'
#3285000
b11011 /
1'
#3290000
0'
#3295000
b11100 /
1'
#3300000
0'
#3305000
b11101 /
1'
#3310000
0'
#3315000
b11110 /
1'
#3320000
0'
#3325000
b11111 /
1'
#3330000
0'
#3335000
b100000 /
1'
#3340000
0'
#3345000
b100001 /
1'
#3350000
0'
#3355000
b100010 /
1'
#3360000
0'
#3365000
b100011 /
1'
#3370000
0'
#3375000
b100100 /
1'
#3380000
0'
#3385000
b100101 /
1'
#3390000
0'
#3395000
b100110 /
1'
#3400000
0'
#3405000
b100111 /
1'
#3410000
0'
#3415000
b101000 /
1'
#3420000
0'
#3425000
b101001 /
1'
#3430000
0'
#3435000
b101010 /
1'
#3440000
0'
#3445000
b101011 /
1'
#3450000
0'
#3455000
b101100 /
1'
#3460000
0'
#3465000
b101101 /
1'
#3470000
0'
#3475000
b101110 /
1'
#3480000
0'
#3485000
b101111 /
1'
#3490000
0'
#3495000
b110000 /
1'
#3500000
0'
#3505000
b110001 /
1'
#3510000
0'
#3515000
b0 /
12
1'
#3520000
0'
#3525000
b111 3
b1 /
02
1'
#3530000
0'
#3535000
b10 /
1'
#3540000
0'
#3545000
b11 /
1'
#3550000
0'
#3555000
b100 /
1'
#3560000
0'
#3565000
b101 /
1'
#3570000
0'
#3575000
b110 /
1'
#3580000
0'
#3585000
b111 /
1'
#3590000
0'
#3595000
b1000 /
1'
#3600000
0'
#3605000
b1001 /
1'
#3610000
0'
#3615000
b1010 /
1'
#3620000
0'
#3625000
b1011 /
1'
#3630000
0'
#3635000
b1100 /
1'
#3640000
0'
#3645000
b1101 /
1'
#3650000
0'
#3655000
b1110 /
1'
#3660000
0'
#3665000
b1111 /
1'
#3670000
0'
#3675000
b10000 /
1'
#3680000
0'
#3685000
b10001 /
1'
#3690000
0'
#3695000
b10010 /
1'
#3700000
0'
#3705000
b10011 /
1'
#3710000
0'
#3715000
b10100 /
1'
#3720000
0'
#3725000
b10101 /
1'
#3730000
0'
#3735000
b10110 /
1'
#3740000
0'
#3745000
b10111 /
1'
#3750000
0'
#3755000
b11000 /
1'
#3760000
0'
#3765000
b11001 /
1'
#3770000
0'
#3775000
b11010 /
1'
#3780000
0'
#3785000
b11011 /
1'
#3790000
0'
#3795000
b11100 /
1'
#3800000
0'
#3805000
b11101 /
1'
#3810000
0'
#3815000
b11110 /
1'
#3820000
0'
#3825000
b11111 /
1'
#3830000
0'
#3835000
b100000 /
1'
#3840000
0'
#3845000
b100001 /
1'
#3850000
0'
#3855000
b100010 /
1'
#3860000
0'
#3865000
b100011 /
1'
#3870000
0'
#3875000
b100100 /
1'
#3880000
0'
#3885000
b100101 /
1'
#3890000
0'
#3895000
b100110 /
1'
#3900000
0'
#3905000
b100111 /
1'
#3910000
0'
#3915000
b101000 /
1'
#3920000
0'
#3925000
b101001 /
1'
#3930000
0'
#3935000
b101010 /
1'
#3940000
0'
#3945000
b101011 /
1'
#3950000
0'
#3955000
b101100 /
1'
#3960000
0'
#3965000
b101101 /
1'
#3970000
0'
#3975000
b101110 /
1'
#3980000
0'
#3985000
b101111 /
1'
#3990000
0'
#3995000
b110000 /
1'
#4000000
0'
#4005000
b110001 /
1'
#4010000
0'
#4015000
b0 /
12
1'
#4020000
0'
#4025000
b1000 3
b1 /
02
1'
#4030000
0'
#4035000
b10 /
1'
#4040000
b1 0
0'
1)
#4045000
1!
1%
0#
b1 1
b11 /
1'
#4050000
0'
#4055000
b100 /
1'
#4060000
0'
0)
#4065000
b101 /
1'
#4070000
0'
#4075000
b110 /
1'
#4080000
0'
#4085000
b111 /
1'
#4090000
0'
#4095000
b1000 /
1'
#4100000
0'
#4105000
b1001 /
1'
#4110000
0'
#4115000
b1010 /
1'
#4120000
0'
#4125000
b1011 /
1'
#4130000
0'
#4135000
b1100 /
1'
#4140000
0'
#4145000
b1101 /
1'
#4150000
0'
#4155000
b1110 /
1'
#4160000
0'
#4165000
b1111 /
1'
#4170000
0'
#4175000
b10000 /
1'
#4180000
0'
#4185000
b10001 /
1'
#4190000
0'
#4195000
b10010 /
1'
#4200000
0'
#4205000
b10011 /
1'
#4210000
0'
#4215000
b10100 /
1'
#4220000
0'
#4225000
b10101 /
1'
#4230000
0'
#4235000
b10110 /
1'
#4240000
0'
#4245000
b10111 /
1'
#4250000
0'
#4255000
b11000 /
1'
#4260000
0'
#4265000
b11001 /
1'
#4270000
0'
#4275000
b11010 /
1'
#4280000
0'
#4285000
b11011 /
1'
#4290000
0'
#4295000
b11100 /
1'
#4300000
0'
#4305000
b11101 /
1'
#4310000
0'
#4315000
b11110 /
1'
#4320000
0'
#4325000
b11111 /
1'
#4330000
0'
#4335000
b100000 /
1'
#4340000
0'
#4345000
b100001 /
1'
#4350000
0'
#4355000
b100010 /
1'
#4360000
0'
#4365000
b100011 /
1'
#4370000
0'
#4375000
b100100 /
1'
#4380000
0'
#4385000
b100101 /
1'
#4390000
0'
#4395000
b100110 /
1'
#4400000
0'
#4405000
b100111 /
1'
#4410000
0'
#4415000
b101000 /
1'
#4420000
0'
#4425000
b101001 /
1'
#4430000
0'
#4435000
b101010 /
1'
#4440000
0'
#4445000
b101011 /
1'
#4450000
0'
#4455000
b101100 /
1'
#4460000
0'
#4465000
b101101 /
1'
#4470000
0'
#4475000
b101110 /
1'
#4480000
0'
#4485000
b101111 /
1'
#4490000
0'
#4495000
b110000 /
1'
#4500000
0'
#4505000
b110001 /
1'
#4510000
0'
#4515000
b0 /
12
1'
#4520000
0'
#4525000
b1001 3
b1 /
02
1'
#4530000
0'
#4535000
b10 /
1'
#4540000
0'
#4545000
b11 /
1'
#4550000
0'
#4555000
b100 /
1'
#4560000
0'
#4565000
b101 /
1'
#4570000
0'
#4575000
b110 /
1'
#4580000
0'
#4585000
b111 /
1'
#4590000
0'
#4595000
b1000 /
1'
#4600000
0'
#4605000
b1001 /
1'
#4610000
0'
#4615000
b1010 /
1'
#4620000
0'
#4625000
b1011 /
1'
#4630000
0'
#4635000
b1100 /
1'
#4640000
0'
#4645000
b1101 /
1'
#4650000
0'
#4655000
b1110 /
1'
#4660000
0'
#4665000
b1111 /
1'
#4670000
0'
#4675000
b10000 /
1'
#4680000
0'
#4685000
b10001 /
1'
#4690000
0'
#4695000
b10010 /
1'
#4700000
0'
#4705000
b10011 /
1'
#4710000
0'
#4715000
b10100 /
1'
#4720000
0'
#4725000
b10101 /
1'
#4730000
0'
#4735000
b10110 /
1'
#4740000
0'
#4745000
b10111 /
1'
#4750000
0'
#4755000
b11000 /
1'
#4760000
0'
#4765000
b11001 /
1'
#4770000
0'
#4775000
b11010 /
1'
#4780000
0'
#4785000
b11011 /
1'
#4790000
0'
#4795000
b11100 /
1'
#4800000
0'
#4805000
b11101 /
1'
#4810000
0'
#4815000
b11110 /
1'
#4820000
0'
#4825000
b11111 /
1'
#4830000
0'
#4835000
b100000 /
1'
#4840000
0'
#4845000
b100001 /
1'
#4850000
0'
#4855000
b100010 /
1'
#4860000
0'
#4865000
b100011 /
1'
#4870000
0'
#4875000
b100100 /
1'
#4880000
0'
#4885000
b100101 /
1'
#4890000
0'
#4895000
b100110 /
1'
#4900000
0'
#4905000
b100111 /
1'
#4910000
0'
#4915000
b101000 /
1'
#4920000
0'
#4925000
b101001 /
1'
#4930000
0'
#4935000
b101010 /
1'
#4940000
0'
#4945000
b101011 /
1'
#4950000
0'
#4955000
b101100 /
1'
#4960000
0'
#4965000
b101101 /
1'
#4970000
0'
#4975000
b101110 /
1'
#4980000
0'
#4985000
b101111 /
1'
#4990000
0'
#4995000
b110000 /
1'
#5000000
0'
#5005000
b110001 /
1'
#5010000
0'
#5015000
b0 /
12
1'
#5020000
0'
#5025000
b1010 3
b1 /
02
1'
#5030000
0'
#5035000
b10 /
1'
#5040000
0'
#5045000
b11 /
1'
#5050000
0'
#5055000
b100 /
1'
#5060000
0'
#5065000
b101 /
1'
#5070000
0'
#5075000
b110 /
1'
#5080000
0'
#5085000
b111 /
1'
#5090000
0'
#5095000
b1000 /
1'
#5100000
0'
#5105000
b1001 /
1'
#5110000
0'
#5115000
b1010 /
1'
#5120000
0'
#5125000
b1011 /
1'
#5130000
0'
#5135000
b1100 /
1'
#5140000
0'
#5145000
b1101 /
1'
#5150000
0'
#5155000
b1110 /
1'
#5160000
0'
#5165000
b1111 /
1'
#5170000
0'
#5175000
b10000 /
1'
#5180000
0'
#5185000
b10001 /
1'
#5190000
0'
#5195000
b10010 /
1'
#5200000
0'
#5205000
b10011 /
1'
#5210000
0'
#5215000
b10100 /
1'
#5220000
0'
#5225000
b10101 /
1'
#5230000
0'
#5235000
b10110 /
1'
#5240000
0'
#5245000
b10111 /
1'
#5250000
0'
#5255000
b11000 /
1'
#5260000
0'
#5265000
b11001 /
1'
#5270000
0'
#5275000
b11010 /
1'
#5280000
0'
#5285000
b11011 /
1'
#5290000
0'
#5295000
b11100 /
1'
#5300000
0'
#5305000
b11101 /
1'
#5310000
0'
#5315000
b11110 /
1'
#5320000
0'
#5325000
b11111 /
1'
#5330000
0'
#5335000
b100000 /
1'
#5340000
0'
#5345000
b100001 /
1'
#5350000
0'
#5355000
b100010 /
1'
#5360000
0'
#5365000
b100011 /
1'
#5370000
0'
#5375000
b100100 /
1'
#5380000
0'
#5385000
b100101 /
1'
#5390000
0'
#5395000
b100110 /
1'
#5400000
0'
#5405000
b100111 /
1'
#5410000
0'
#5415000
b101000 /
1'
#5420000
0'
#5425000
b101001 /
1'
#5430000
0'
#5435000
b101010 /
1'
#5440000
0'
#5445000
b101011 /
1'
#5450000
0'
#5455000
b101100 /
1'
#5460000
0'
#5465000
b101101 /
1'
#5470000
0'
#5475000
b101110 /
1'
#5480000
0'
#5485000
b101111 /
1'
#5490000
0'
#5495000
b110000 /
1'
#5500000
0'
#5505000
b110001 /
1'
#5510000
0'
#5515000
b0 /
12
1'
#5520000
0'
#5525000
b1011 3
b1 /
02
1'
#5530000
0'
#5535000
b10 /
1'
#5540000
0'
#5545000
b11 /
1'
#5550000
0'
#5555000
b100 /
1'
#5560000
0'
#5565000
b101 /
1'
#5570000
0'
#5575000
b110 /
1'
#5580000
0'
#5585000
b111 /
1'
#5590000
0'
#5595000
b1000 /
1'
#5600000
0'
#5605000
b1001 /
1'
#5610000
0'
#5615000
b1010 /
1'
#5620000
0'
#5625000
b1011 /
1'
#5630000
0'
#5635000
b1100 /
1'
#5640000
0'
#5645000
b1101 /
1'
#5650000
0'
#5655000
b1110 /
1'
#5660000
0'
#5665000
b1111 /
1'
#5670000
0'
#5675000
b10000 /
1'
#5680000
0'
#5685000
b10001 /
1'
#5690000
0'
#5695000
b10010 /
1'
#5700000
0'
#5705000
b10011 /
1'
#5710000
0'
#5715000
b10100 /
1'
#5720000
0'
#5725000
b10101 /
1'
#5730000
0'
#5735000
b10110 /
1'
#5740000
0'
#5745000
b10111 /
1'
#5750000
0'
#5755000
b11000 /
1'
#5760000
0'
